tapsage/__init__.py
tapsage/tapsagebot.py
tapsage/taptypes.py
tapsage/tapuser.py
tapsage/async_tapsage/__init__.py
tapsage/async_tapsage/asynctapbot.py
tapsage/async_tapsage/asynctapuser.py
tapsage_client-0.10.2.dist-info/LICENSE.txt
tapsage_client-0.10.2.dist-info/METADATA
tapsage_client-0.10.2.dist-info/WHEEL
tapsage_client-0.10.2.dist-info/top_level.txt
tapsage_client-0.10.2.dist-info/RECORD
