Metadata-Version: 2.1
Name: tapsage_client
Version: 0.10.2
Summary: A Python client for Tapsage to streamline API interactions, enabling easy management and customization of AI-driven chatbots and image models.
Author-email: Mahdi Kiani <mahdi@mahdikiani.com>
Maintainer-email: Mahdi Kiani <mahdi@mahdikiani.com>
License:                                  Apache License
Project-URL: Homepage, https://github.com/mahdikiani/tapsage-python
Project-URL: Bug Reports, https://github.com/mahdikiani/tapsage-python/issues
Project-URL: Funding, https://github.com/mahdikiani/tapsage-python
Project-URL: Say Thanks!, https://saythanks.io/to/mahdikiani
Project-URL: Source, https://github.com/mahdikiani/tapsage-python
Keywords: tapsage,ai,llm,api,generative ai
Classifier: Development Status :: 4 - Beta
Classifier: Intended Audience :: Developers
Classifier: Topic :: Software Development :: Build Tools
Classifier: License :: OSI Approved :: MIT License
Classifier: Programming Language :: Python :: 3
Classifier: Programming Language :: Python :: 3.8
Classifier: Programming Language :: Python :: 3.9
Classifier: Programming Language :: Python :: 3.10
Classifier: Programming Language :: Python :: 3.11
Classifier: Programming Language :: Python :: 3.12
Classifier: Programming Language :: Python :: 3 :: Only
Requires-Python: >=3.8
License-File: LICENSE.txt
Requires-Dist: pydantic>=1.8.2
Requires-Dist: requests>=2.26.0
Requires-Dist: httpx>=0.20.0
Provides-Extra: dev
Requires-Dist: check-manifest; extra == "dev"
Provides-Extra: test
Requires-Dist: coverage; extra == "test"
